agora_busclient/__init__.py
agora_busclient/base_nats_client.py
agora_busclient/bus_client.py
agora_busclient/message_queue.py
agora_busclient/nats_client.py
agora_busclient/version.py
agora_busclient/messages/__init__.py
agora_busclient/messages/dict_of_str.py
agora_busclient/messages/event_msg.py
agora_busclient/messages/io_device_data.py
agora_busclient/messages/io_point.py
agora_busclient/messages/io_tag_data_dict.py
agora_busclient/messages/iodatareport_message.py
agora_busclient/messages/media_data.py
agora_busclient/messages/message_header.py
agora_busclient/messages/msg_decoder.py
agora_busclient/messages/msg_encoder.py
agora_busclient/messages/request_msg.py
agora_busclient/messages/work_flow.py
agora_busclient-3.0.2.dist-info/licenses/LICENSE
agora_busclient-3.0.2.dist-info/WHEEL
agora_busclient-3.0.2.dist-info/METADATA
agora_busclient-3.0.2.dist-info/RECORD
