Metadata-Version: 2.4
Name: agora_busclient
Version: 3.0.2
Summary: Bus Client libraries for the Agora Edge Apps SDK 2.0 (Python)
Author-email: AgoraIoT <agoraiot@slb.com>
Classifier: License :: OSI Approved :: Apache Software License
License-File: LICENSE
Requires-Dist: agora_logging == 3.0.2
Requires-Dist: agora_config == 3.0.2
Requires-Dist: agora_utils == 3.0.2
Requires-Dist: nats-py
Requires-Dist: nest_asyncio
Requires-Dist: requests
Project-URL: Home, https://agoraiot.github.io
